[{"arguments":["clang","-Wno-documentation-unknown-command","-Wno-unknown-warning-option","-Wno-unknown-pragmas","-nostdinc","-nostdinc++","-g","-std=gnu++1z","-Wall","-Wextra","-Wextra","-fexceptions","-mthreads","-fsyntax-only","-m64","--target=x86_64-w64-mingw32","-DUNICODE","-D_UNICODE","-DWIN32","-DMINGW_HAS_SECURE_API","-DQT_QML_DEBUG","-DQT_WIDGETS_LIB","-DQT_GUI_LIB","-DQT_CORE_LIB","-DQT_NEEDS_QMAIN","-DQ_CREATOR_RUN","-DQT_ANNOTATE_FUNCTION(x)=__attribute__((annotate(#x)))","-ID:\\QT\\Tools\\QtCreator\\share\\qtcreator\\cplusplus\\wrappedMingwHeaders","-ID:\\QT\\Tools\\QtCreator\\share\\qtcreator\\cplusplus\\wrappedQtHeaders","-ID:\\QT\\Tools\\QtCreator\\share\\qtcreator\\cplusplus\\wrappedQtHeaders\\QtCore","-ID:\\fly_manage_system_lxt","-ID:\\QT\\6.8.0\\mingw_64\\include","-ID:\\QT\\6.8.0\\mingw_64\\include\\QtWidgets","-ID:\\QT\\6.8.0\\mingw_64\\include\\QtGui","-ID:\\QT\\6.8.0\\mingw_64\\include\\QtCore","-ID:\\fly_manage_system_lxt\\build\\Desktop_Qt_6_8_0_MinGW_64_bit-Debug\\debug","-ID:\\fly_manage_system_lxt\\build\\Desktop_Qt_6_8_0_MinGW_64_bit-Debug","-ID:\\QT\\6.8.0\\mingw_64\\mkspecs\\win32-g++","-isystem","D:\\QT\\Tools\\mingw1310_64\\lib\\gcc\\x86_64-w64-mingw32\\13.1.0\\include\\c++","-isystem","D:\\QT\\Tools\\mingw1310_64\\lib\\gcc\\x86_64-w64-mingw32\\13.1.0\\include\\c++\\x86_64-w64-mingw32","-isystem","D:\\QT\\Tools\\mingw1310_64\\lib\\gcc\\x86_64-w64-mingw32\\13.1.0\\include\\c++\\backward","-isystem","D:\\QT\\Tools\\QtCreator\\bin\\clang\\lib\\clang\\18\\include","-isystem","D:\\QT\\Tools\\mingw1310_64\\x86_64-w64-mingw32\\include","-fmessage-length=0","-fdiagnostics-show-note-include-stack","-fretain-comments-from-system-headers","-fmacro-backtrace-limit=0","-ferror-limit=1000","-x","c++","D:\\fly_manage_system_lxt\\betawindow.cpp"],"directory":"D:/fly_manage_system_lxt/build/Desktop_Qt_6_8_0_MinGW_64_bit-Debug/.qtc_clangd","file":"D:/fly_manage_system_lxt/betawindow.cpp"},{"arguments":["clang","-Wno-documentation-unknown-command","-Wno-unknown-warning-option","-Wno-unknown-pragmas","-nostdinc","-nostdinc++","-g","-std=gnu++1z","-Wall","-Wextra","-Wextra","-fexceptions","-mthreads","-fsyntax-only","-m64","--target=x86_64-w64-mingw32","-DUNICODE","-D_UNICODE","-DWIN32","-DMINGW_HAS_SECURE_API","-DQT_QML_DEBUG","-DQT_WIDGETS_LIB","-DQT_GUI_LIB","-DQT_CORE_LIB","-DQT_NEEDS_QMAIN","-DQ_CREATOR_RUN","-DQT_ANNOTATE_FUNCTION(x)=__attribute__((annotate(#x)))","-ID:\\QT\\Tools\\QtCreator\\share\\qtcreator\\cplusplus\\wrappedMingwHeaders","-ID:\\QT\\Tools\\QtCreator\\share\\qtcreator\\cplusplus\\wrappedQtHeaders","-ID:\\QT\\Tools\\QtCreator\\share\\qtcreator\\cplusplus\\wrappedQtHeaders\\QtCore","-ID:\\fly_manage_system_lxt","-ID:\\QT\\6.8.0\\mingw_64\\include","-ID:\\QT\\6.8.0\\mingw_64\\include\\QtWidgets","-ID:\\QT\\6.8.0\\mingw_64\\include\\QtGui","-ID:\\QT\\6.8.0\\mingw_64\\include\\QtCore","-ID:\\fly_manage_system_lxt\\build\\Desktop_Qt_6_8_0_MinGW_64_bit-Debug\\debug","-ID:\\fly_manage_system_lxt\\build\\Desktop_Qt_6_8_0_MinGW_64_bit-Debug","-ID:\\QT\\6.8.0\\mingw_64\\mkspecs\\win32-g++","-isystem","D:\\QT\\Tools\\mingw1310_64\\lib\\gcc\\x86_64-w64-mingw32\\13.1.0\\include\\c++","-isystem","D:\\QT\\Tools\\mingw1310_64\\lib\\gcc\\x86_64-w64-mingw32\\13.1.0\\include\\c++\\x86_64-w64-mingw32","-isystem","D:\\QT\\Tools\\mingw1310_64\\lib\\gcc\\x86_64-w64-mingw32\\13.1.0\\include\\c++\\backward","-isystem","D:\\QT\\Tools\\QtCreator\\bin\\clang\\lib\\clang\\18\\include","-isystem","D:\\QT\\Tools\\mingw1310_64\\x86_64-w64-mingw32\\include","-fmessage-length=0","-fdiagnostics-show-note-include-stack","-fretain-comments-from-system-headers","-fmacro-backtrace-limit=0","-ferror-limit=1000","-x","c++","D:\\fly_manage_system_lxt\\gamawindow.cpp"],"directory":"D:/fly_manage_system_lxt/build/Desktop_Qt_6_8_0_MinGW_64_bit-Debug/.qtc_clangd","file":"D:/fly_manage_system_lxt/gamawindow.cpp"},{"arguments":["clang","-Wno-documentation-unknown-command","-Wno-unknown-warning-option","-Wno-unknown-pragmas","-nostdinc","-nostdinc++","-g","-std=gnu++1z","-Wall","-Wextra","-Wextra","-fexceptions","-mthreads","-fsyntax-only","-m64","--target=x86_64-w64-mingw32","-DUNICODE","-D_UNICODE","-DWIN32","-DMINGW_HAS_SECURE_API","-DQT_QML_DEBUG","-DQT_WIDGETS_LIB","-DQT_GUI_LIB","-DQT_CORE_LIB","-DQT_NEEDS_QMAIN","-DQ_CREATOR_RUN","-DQT_ANNOTATE_FUNCTION(x)=__attribute__((annotate(#x)))","-ID:\\QT\\Tools\\QtCreator\\share\\qtcreator\\cplusplus\\wrappedMingwHeaders","-ID:\\QT\\Tools\\QtCreator\\share\\qtcreator\\cplusplus\\wrappedQtHeaders","-ID:\\QT\\Tools\\QtCreator\\share\\qtcreator\\cplusplus\\wrappedQtHeaders\\QtCore","-ID:\\fly_manage_system_lxt","-ID:\\QT\\6.8.0\\mingw_64\\include","-ID:\\QT\\6.8.0\\mingw_64\\include\\QtWidgets","-ID:\\QT\\6.8.0\\mingw_64\\include\\QtGui","-ID:\\QT\\6.8.0\\mingw_64\\include\\QtCore","-ID:\\fly_manage_system_lxt\\build\\Desktop_Qt_6_8_0_MinGW_64_bit-Debug\\debug","-ID:\\fly_manage_system_lxt\\build\\Desktop_Qt_6_8_0_MinGW_64_bit-Debug","-ID:\\QT\\6.8.0\\mingw_64\\mkspecs\\win32-g++","-isystem","D:\\QT\\Tools\\mingw1310_64\\lib\\gcc\\x86_64-w64-mingw32\\13.1.0\\include\\c++","-isystem","D:\\QT\\Tools\\mingw1310_64\\lib\\gcc\\x86_64-w64-mingw32\\13.1.0\\include\\c++\\x86_64-w64-mingw32","-isystem","D:\\QT\\Tools\\mingw1310_64\\lib\\gcc\\x86_64-w64-mingw32\\13.1.0\\include\\c++\\backward","-isystem","D:\\QT\\Tools\\QtCreator\\bin\\clang\\lib\\clang\\18\\include","-isystem","D:\\QT\\Tools\\mingw1310_64\\x86_64-w64-mingw32\\include","-fmessage-length=0","-fdiagnostics-show-note-include-stack","-fretain-comments-from-system-headers","-fmacro-backtrace-limit=0","-ferror-limit=1000","-x","c++","D:\\fly_manage_system_lxt\\interfacemanager.cpp"],"directory":"D:/fly_manage_system_lxt/build/Desktop_Qt_6_8_0_MinGW_64_bit-Debug/.qtc_clangd","file":"D:/fly_manage_system_lxt/interfacemanager.cpp"},{"arguments":["clang","-Wno-documentation-unknown-command","-Wno-unknown-warning-option","-Wno-unknown-pragmas","-nostdinc","-nostdinc++","-g","-std=gnu++1z","-Wall","-Wextra","-Wextra","-fexceptions","-mthreads","-fsyntax-only","-m64","--target=x86_64-w64-mingw32","-DUNICODE","-D_UNICODE","-DWIN32","-DMINGW_HAS_SECURE_API","-DQT_QML_DEBUG","-DQT_WIDGETS_LIB","-DQT_GUI_LIB","-DQT_CORE_LIB","-DQT_NEEDS_QMAIN","-DQ_CREATOR_RUN","-DQT_ANNOTATE_FUNCTION(x)=__attribute__((annotate(#x)))","-ID:\\QT\\Tools\\QtCreator\\share\\qtcreator\\cplusplus\\wrappedMingwHeaders","-ID:\\QT\\Tools\\QtCreator\\share\\qtcreator\\cplusplus\\wrappedQtHeaders","-ID:\\QT\\Tools\\QtCreator\\share\\qtcreator\\cplusplus\\wrappedQtHeaders\\QtCore","-ID:\\fly_manage_system_lxt","-ID:\\QT\\6.8.0\\mingw_64\\include","-ID:\\QT\\6.8.0\\mingw_64\\include\\QtWidgets","-ID:\\QT\\6.8.0\\mingw_64\\include\\QtGui","-ID:\\QT\\6.8.0\\mingw_64\\include\\QtCore","-ID:\\fly_manage_system_lxt\\build\\Desktop_Qt_6_8_0_MinGW_64_bit-Debug\\debug","-ID:\\fly_manage_system_lxt\\build\\Desktop_Qt_6_8_0_MinGW_64_bit-Debug","-ID:\\QT\\6.8.0\\mingw_64\\mkspecs\\win32-g++","-isystem","D:\\QT\\Tools\\mingw1310_64\\lib\\gcc\\x86_64-w64-mingw32\\13.1.0\\include\\c++","-isystem","D:\\QT\\Tools\\mingw1310_64\\lib\\gcc\\x86_64-w64-mingw32\\13.1.0\\include\\c++\\x86_64-w64-mingw32","-isystem","D:\\QT\\Tools\\mingw1310_64\\lib\\gcc\\x86_64-w64-mingw32\\13.1.0\\include\\c++\\backward","-isystem","D:\\QT\\Tools\\QtCreator\\bin\\clang\\lib\\clang\\18\\include","-isystem","D:\\QT\\Tools\\mingw1310_64\\x86_64-w64-mingw32\\include","-fmessage-length=0","-fdiagnostics-show-note-include-stack","-fretain-comments-from-system-headers","-fmacro-backtrace-limit=0","-ferror-limit=1000","-x","c++","D:\\fly_manage_system_lxt\\main.cpp"],"directory":"D:/fly_manage_system_lxt/build/Desktop_Qt_6_8_0_MinGW_64_bit-Debug/.qtc_clangd","file":"D:/fly_manage_system_lxt/main.cpp"},{"arguments":["clang","-Wno-documentation-unknown-command","-Wno-unknown-warning-option","-Wno-unknown-pragmas","-nostdinc","-nostdinc++","-g","-std=gnu++1z","-Wall","-Wextra","-Wextra","-fexceptions","-mthreads","-fsyntax-only","-m64","--target=x86_64-w64-mingw32","-DUNICODE","-D_UNICODE","-DWIN32","-DMINGW_HAS_SECURE_API","-DQT_QML_DEBUG","-DQT_WIDGETS_LIB","-DQT_GUI_LIB","-DQT_CORE_LIB","-DQT_NEEDS_QMAIN","-DQ_CREATOR_RUN","-DQT_ANNOTATE_FUNCTION(x)=__attribute__((annotate(#x)))","-ID:\\QT\\Tools\\QtCreator\\share\\qtcreator\\cplusplus\\wrappedMingwHeaders","-ID:\\QT\\Tools\\QtCreator\\share\\qtcreator\\cplusplus\\wrappedQtHeaders","-ID:\\QT\\Tools\\QtCreator\\share\\qtcreator\\cplusplus\\wrappedQtHeaders\\QtCore","-ID:\\fly_manage_system_lxt","-ID:\\QT\\6.8.0\\mingw_64\\include","-ID:\\QT\\6.8.0\\mingw_64\\include\\QtWidgets","-ID:\\QT\\6.8.0\\mingw_64\\include\\QtGui","-ID:\\QT\\6.8.0\\mingw_64\\include\\QtCore","-ID:\\fly_manage_system_lxt\\build\\Desktop_Qt_6_8_0_MinGW_64_bit-Debug\\debug","-ID:\\fly_manage_system_lxt\\build\\Desktop_Qt_6_8_0_MinGW_64_bit-Debug","-ID:\\QT\\6.8.0\\mingw_64\\mkspecs\\win32-g++","-isystem","D:\\QT\\Tools\\mingw1310_64\\lib\\gcc\\x86_64-w64-mingw32\\13.1.0\\include\\c++","-isystem","D:\\QT\\Tools\\mingw1310_64\\lib\\gcc\\x86_64-w64-mingw32\\13.1.0\\include\\c++\\x86_64-w64-mingw32","-isystem","D:\\QT\\Tools\\mingw1310_64\\lib\\gcc\\x86_64-w64-mingw32\\13.1.0\\include\\c++\\backward","-isystem","D:\\QT\\Tools\\QtCreator\\bin\\clang\\lib\\clang\\18\\include","-isystem","D:\\QT\\Tools\\mingw1310_64\\x86_64-w64-mingw32\\include","-fmessage-length=0","-fdiagnostics-show-note-include-stack","-fretain-comments-from-system-headers","-fmacro-backtrace-limit=0","-ferror-limit=1000","-x","c++","D:\\fly_manage_system_lxt\\mainwindow.cpp"],"directory":"D:/fly_manage_system_lxt/build/Desktop_Qt_6_8_0_MinGW_64_bit-Debug/.qtc_clangd","file":"D:/fly_manage_system_lxt/mainwindow.cpp"},{"arguments":["clang","-Wno-documentation-unknown-command","-Wno-unknown-warning-option","-Wno-unknown-pragmas","-nostdinc","-nostdinc++","-g","-std=gnu++1z","-Wall","-Wextra","-Wextra","-fexceptions","-mthreads","-fsyntax-only","-m64","--target=x86_64-w64-mingw32","-DUNICODE","-D_UNICODE","-DWIN32","-DMINGW_HAS_SECURE_API","-DQT_QML_DEBUG","-DQT_WIDGETS_LIB","-DQT_GUI_LIB","-DQT_CORE_LIB","-DQT_NEEDS_QMAIN","-DQ_CREATOR_RUN","-DQT_ANNOTATE_FUNCTION(x)=__attribute__((annotate(#x)))","-ID:\\QT\\Tools\\QtCreator\\share\\qtcreator\\cplusplus\\wrappedMingwHeaders","-ID:\\QT\\Tools\\QtCreator\\share\\qtcreator\\cplusplus\\wrappedQtHeaders","-ID:\\QT\\Tools\\QtCreator\\share\\qtcreator\\cplusplus\\wrappedQtHeaders\\QtCore","-ID:\\fly_manage_system_lxt","-ID:\\QT\\6.8.0\\mingw_64\\include","-ID:\\QT\\6.8.0\\mingw_64\\include\\QtWidgets","-ID:\\QT\\6.8.0\\mingw_64\\include\\QtGui","-ID:\\QT\\6.8.0\\mingw_64\\include\\QtCore","-ID:\\fly_manage_system_lxt\\build\\Desktop_Qt_6_8_0_MinGW_64_bit-Debug\\debug","-ID:\\fly_manage_system_lxt\\build\\Desktop_Qt_6_8_0_MinGW_64_bit-Debug","-ID:\\QT\\6.8.0\\mingw_64\\mkspecs\\win32-g++","-isystem","D:\\QT\\Tools\\mingw1310_64\\lib\\gcc\\x86_64-w64-mingw32\\13.1.0\\include\\c++","-isystem","D:\\QT\\Tools\\mingw1310_64\\lib\\gcc\\x86_64-w64-mingw32\\13.1.0\\include\\c++\\x86_64-w64-mingw32","-isystem","D:\\QT\\Tools\\mingw1310_64\\lib\\gcc\\x86_64-w64-mingw32\\13.1.0\\include\\c++\\backward","-isystem","D:\\QT\\Tools\\QtCreator\\bin\\clang\\lib\\clang\\18\\include","-isystem","D:\\QT\\Tools\\mingw1310_64\\x86_64-w64-mingw32\\include","-fmessage-length=0","-fdiagnostics-show-note-include-stack","-fretain-comments-from-system-headers","-fmacro-backtrace-limit=0","-ferror-limit=1000","-x","c++","D:\\fly_manage_system_lxt\\xitawindow.cpp"],"directory":"D:/fly_manage_system_lxt/build/Desktop_Qt_6_8_0_MinGW_64_bit-Debug/.qtc_clangd","file":"D:/fly_manage_system_lxt/xitawindow.cpp"},{"arguments":["clang","-Wno-documentation-unknown-command","-Wno-unknown-warning-option","-Wno-unknown-pragmas","-nostdinc","-nostdinc++","-g","-std=gnu++1z","-Wall","-Wextra","-Wextra","-fexceptions","-mthreads","-fsyntax-only","-m64","--target=x86_64-w64-mingw32","-DUNICODE","-D_UNICODE","-DWIN32","-DMINGW_HAS_SECURE_API","-DQT_QML_DEBUG","-DQT_WIDGETS_LIB","-DQT_GUI_LIB","-DQT_CORE_LIB","-DQT_NEEDS_QMAIN","-DQ_CREATOR_RUN","-DQT_ANNOTATE_FUNCTION(x)=__attribute__((annotate(#x)))","-ID:\\QT\\Tools\\QtCreator\\share\\qtcreator\\cplusplus\\wrappedMingwHeaders","-ID:\\QT\\Tools\\QtCreator\\share\\qtcreator\\cplusplus\\wrappedQtHeaders","-ID:\\QT\\Tools\\QtCreator\\share\\qtcreator\\cplusplus\\wrappedQtHeaders\\QtCore","-ID:\\fly_manage_system_lxt","-ID:\\QT\\6.8.0\\mingw_64\\include","-ID:\\QT\\6.8.0\\mingw_64\\include\\QtWidgets","-ID:\\QT\\6.8.0\\mingw_64\\include\\QtGui","-ID:\\QT\\6.8.0\\mingw_64\\include\\QtCore","-ID:\\fly_manage_system_lxt\\build\\Desktop_Qt_6_8_0_MinGW_64_bit-Debug\\debug","-ID:\\fly_manage_system_lxt\\build\\Desktop_Qt_6_8_0_MinGW_64_bit-Debug","-ID:\\QT\\6.8.0\\mingw_64\\mkspecs\\win32-g++","-isystem","D:\\QT\\Tools\\mingw1310_64\\lib\\gcc\\x86_64-w64-mingw32\\13.1.0\\include\\c++","-isystem","D:\\QT\\Tools\\mingw1310_64\\lib\\gcc\\x86_64-w64-mingw32\\13.1.0\\include\\c++\\x86_64-w64-mingw32","-isystem","D:\\QT\\Tools\\mingw1310_64\\lib\\gcc\\x86_64-w64-mingw32\\13.1.0\\include\\c++\\backward","-isystem","D:\\QT\\Tools\\QtCreator\\bin\\clang\\lib\\clang\\18\\include","-isystem","D:\\QT\\Tools\\mingw1310_64\\x86_64-w64-mingw32\\include","-fmessage-length=0","-fdiagnostics-show-note-include-stack","-fretain-comments-from-system-headers","-fmacro-backtrace-limit=0","-ferror-limit=1000","-x","c++","D:\\fly_manage_system_lxt\\yipuxilong.cpp"],"directory":"D:/fly_manage_system_lxt/build/Desktop_Qt_6_8_0_MinGW_64_bit-Debug/.qtc_clangd","file":"D:/fly_manage_system_lxt/yipuxilong.cpp"},{"arguments":["clang","-Wno-documentation-unknown-command","-Wno-unknown-warning-option","-Wno-unknown-pragmas","-nostdinc","-nostdinc++","-g","-std=gnu++1z","-Wall","-Wextra","-Wextra","-fexceptions","-mthreads","-fsyntax-only","-m64","--target=x86_64-w64-mingw32","-DUNICODE","-D_UNICODE","-DWIN32","-DMINGW_HAS_SECURE_API","-DQT_QML_DEBUG","-DQT_WIDGETS_LIB","-DQT_GUI_LIB","-DQT_CORE_LIB","-DQT_NEEDS_QMAIN","-DQ_CREATOR_RUN","-DQT_ANNOTATE_FUNCTION(x)=__attribute__((annotate(#x)))","-ID:\\QT\\Tools\\QtCreator\\share\\qtcreator\\cplusplus\\wrappedMingwHeaders","-ID:\\QT\\Tools\\QtCreator\\share\\qtcreator\\cplusplus\\wrappedQtHeaders","-ID:\\QT\\Tools\\QtCreator\\share\\qtcreator\\cplusplus\\wrappedQtHeaders\\QtCore","-ID:\\fly_manage_system_lxt","-ID:\\QT\\6.8.0\\mingw_64\\include","-ID:\\QT\\6.8.0\\mingw_64\\include\\QtWidgets","-ID:\\QT\\6.8.0\\mingw_64\\include\\QtGui","-ID:\\QT\\6.8.0\\mingw_64\\include\\QtCore","-ID:\\fly_manage_system_lxt\\build\\Desktop_Qt_6_8_0_MinGW_64_bit-Debug\\debug","-ID:\\fly_manage_system_lxt\\build\\Desktop_Qt_6_8_0_MinGW_64_bit-Debug","-ID:\\QT\\6.8.0\\mingw_64\\mkspecs\\win32-g++","-isystem","D:\\QT\\Tools\\mingw1310_64\\lib\\gcc\\x86_64-w64-mingw32\\13.1.0\\include\\c++","-isystem","D:\\QT\\Tools\\mingw1310_64\\lib\\gcc\\x86_64-w64-mingw32\\13.1.0\\include\\c++\\x86_64-w64-mingw32","-isystem","D:\\QT\\Tools\\mingw1310_64\\lib\\gcc\\x86_64-w64-mingw32\\13.1.0\\include\\c++\\backward","-isystem","D:\\QT\\Tools\\QtCreator\\bin\\clang\\lib\\clang\\18\\include","-isystem","D:\\QT\\Tools\\mingw1310_64\\x86_64-w64-mingw32\\include","-fmessage-length=0","-fdiagnostics-show-note-include-stack","-fretain-comments-from-system-headers","-fmacro-backtrace-limit=0","-ferror-limit=1000","-x","c++-header","D:\\fly_manage_system_lxt\\betawindow.h"],"directory":"D:/fly_manage_system_lxt/build/Desktop_Qt_6_8_0_MinGW_64_bit-Debug/.qtc_clangd","file":"D:/fly_manage_system_lxt/betawindow.h"},{"arguments":["clang","-Wno-documentation-unknown-command","-Wno-unknown-warning-option","-Wno-unknown-pragmas","-nostdinc","-nostdinc++","-g","-std=gnu++1z","-Wall","-Wextra","-Wextra","-fexceptions","-mthreads","-fsyntax-only","-m64","--target=x86_64-w64-mingw32","-DUNICODE","-D_UNICODE","-DWIN32","-DMINGW_HAS_SECURE_API","-DQT_QML_DEBUG","-DQT_WIDGETS_LIB","-DQT_GUI_LIB","-DQT_CORE_LIB","-DQT_NEEDS_QMAIN","-DQ_CREATOR_RUN","-DQT_ANNOTATE_FUNCTION(x)=__attribute__((annotate(#x)))","-ID:\\QT\\Tools\\QtCreator\\share\\qtcreator\\cplusplus\\wrappedMingwHeaders","-ID:\\QT\\Tools\\QtCreator\\share\\qtcreator\\cplusplus\\wrappedQtHeaders","-ID:\\QT\\Tools\\QtCreator\\share\\qtcreator\\cplusplus\\wrappedQtHeaders\\QtCore","-ID:\\fly_manage_system_lxt","-ID:\\QT\\6.8.0\\mingw_64\\include","-ID:\\QT\\6.8.0\\mingw_64\\include\\QtWidgets","-ID:\\QT\\6.8.0\\mingw_64\\include\\QtGui","-ID:\\QT\\6.8.0\\mingw_64\\include\\QtCore","-ID:\\fly_manage_system_lxt\\build\\Desktop_Qt_6_8_0_MinGW_64_bit-Debug\\debug","-ID:\\fly_manage_system_lxt\\build\\Desktop_Qt_6_8_0_MinGW_64_bit-Debug","-ID:\\QT\\6.8.0\\mingw_64\\mkspecs\\win32-g++","-isystem","D:\\QT\\Tools\\mingw1310_64\\lib\\gcc\\x86_64-w64-mingw32\\13.1.0\\include\\c++","-isystem","D:\\QT\\Tools\\mingw1310_64\\lib\\gcc\\x86_64-w64-mingw32\\13.1.0\\include\\c++\\x86_64-w64-mingw32","-isystem","D:\\QT\\Tools\\mingw1310_64\\lib\\gcc\\x86_64-w64-mingw32\\13.1.0\\include\\c++\\backward","-isystem","D:\\QT\\Tools\\QtCreator\\bin\\clang\\lib\\clang\\18\\include","-isystem","D:\\QT\\Tools\\mingw1310_64\\x86_64-w64-mingw32\\include","-fmessage-length=0","-fdiagnostics-show-note-include-stack","-fretain-comments-from-system-headers","-fmacro-backtrace-limit=0","-ferror-limit=1000","-x","c++-header","D:\\fly_manage_system_lxt\\gamawindow.h"],"directory":"D:/fly_manage_system_lxt/build/Desktop_Qt_6_8_0_MinGW_64_bit-Debug/.qtc_clangd","file":"D:/fly_manage_system_lxt/gamawindow.h"},{"arguments":["clang","-Wno-documentation-unknown-command","-Wno-unknown-warning-option","-Wno-unknown-pragmas","-nostdinc","-nostdinc++","-g","-std=gnu++1z","-Wall","-Wextra","-Wextra","-fexceptions","-mthreads","-fsyntax-only","-m64","--target=x86_64-w64-mingw32","-DUNICODE","-D_UNICODE","-DWIN32","-DMINGW_HAS_SECURE_API","-DQT_QML_DEBUG","-DQT_WIDGETS_LIB","-DQT_GUI_LIB","-DQT_CORE_LIB","-DQT_NEEDS_QMAIN","-DQ_CREATOR_RUN","-DQT_ANNOTATE_FUNCTION(x)=__attribute__((annotate(#x)))","-ID:\\QT\\Tools\\QtCreator\\share\\qtcreator\\cplusplus\\wrappedMingwHeaders","-ID:\\QT\\Tools\\QtCreator\\share\\qtcreator\\cplusplus\\wrappedQtHeaders","-ID:\\QT\\Tools\\QtCreator\\share\\qtcreator\\cplusplus\\wrappedQtHeaders\\QtCore","-ID:\\fly_manage_system_lxt","-ID:\\QT\\6.8.0\\mingw_64\\include","-ID:\\QT\\6.8.0\\mingw_64\\include\\QtWidgets","-ID:\\QT\\6.8.0\\mingw_64\\include\\QtGui","-ID:\\QT\\6.8.0\\mingw_64\\include\\QtCore","-ID:\\fly_manage_system_lxt\\build\\Desktop_Qt_6_8_0_MinGW_64_bit-Debug\\debug","-ID:\\fly_manage_system_lxt\\build\\Desktop_Qt_6_8_0_MinGW_64_bit-Debug","-ID:\\QT\\6.8.0\\mingw_64\\mkspecs\\win32-g++","-isystem","D:\\QT\\Tools\\mingw1310_64\\lib\\gcc\\x86_64-w64-mingw32\\13.1.0\\include\\c++","-isystem","D:\\QT\\Tools\\mingw1310_64\\lib\\gcc\\x86_64-w64-mingw32\\13.1.0\\include\\c++\\x86_64-w64-mingw32","-isystem","D:\\QT\\Tools\\mingw1310_64\\lib\\gcc\\x86_64-w64-mingw32\\13.1.0\\include\\c++\\backward","-isystem","D:\\QT\\Tools\\QtCreator\\bin\\clang\\lib\\clang\\18\\include","-isystem","D:\\QT\\Tools\\mingw1310_64\\x86_64-w64-mingw32\\include","-fmessage-length=0","-fdiagnostics-show-note-include-stack","-fretain-comments-from-system-headers","-fmacro-backtrace-limit=0","-ferror-limit=1000","-x","c++-header","D:\\fly_manage_system_lxt\\interfacemanager.h"],"directory":"D:/fly_manage_system_lxt/build/Desktop_Qt_6_8_0_MinGW_64_bit-Debug/.qtc_clangd","file":"D:/fly_manage_system_lxt/interfacemanager.h"},{"arguments":["clang","-Wno-documentation-unknown-command","-Wno-unknown-warning-option","-Wno-unknown-pragmas","-nostdinc","-nostdinc++","-g","-std=gnu++1z","-Wall","-Wextra","-Wextra","-fexceptions","-mthreads","-fsyntax-only","-m64","--target=x86_64-w64-mingw32","-DUNICODE","-D_UNICODE","-DWIN32","-DMINGW_HAS_SECURE_API","-DQT_QML_DEBUG","-DQT_WIDGETS_LIB","-DQT_GUI_LIB","-DQT_CORE_LIB","-DQT_NEEDS_QMAIN","-DQ_CREATOR_RUN","-DQT_ANNOTATE_FUNCTION(x)=__attribute__((annotate(#x)))","-ID:\\QT\\Tools\\QtCreator\\share\\qtcreator\\cplusplus\\wrappedMingwHeaders","-ID:\\QT\\Tools\\QtCreator\\share\\qtcreator\\cplusplus\\wrappedQtHeaders","-ID:\\QT\\Tools\\QtCreator\\share\\qtcreator\\cplusplus\\wrappedQtHeaders\\QtCore","-ID:\\fly_manage_system_lxt","-ID:\\QT\\6.8.0\\mingw_64\\include","-ID:\\QT\\6.8.0\\mingw_64\\include\\QtWidgets","-ID:\\QT\\6.8.0\\mingw_64\\include\\QtGui","-ID:\\QT\\6.8.0\\mingw_64\\include\\QtCore","-ID:\\fly_manage_system_lxt\\build\\Desktop_Qt_6_8_0_MinGW_64_bit-Debug\\debug","-ID:\\fly_manage_system_lxt\\build\\Desktop_Qt_6_8_0_MinGW_64_bit-Debug","-ID:\\QT\\6.8.0\\mingw_64\\mkspecs\\win32-g++","-isystem","D:\\QT\\Tools\\mingw1310_64\\lib\\gcc\\x86_64-w64-mingw32\\13.1.0\\include\\c++","-isystem","D:\\QT\\Tools\\mingw1310_64\\lib\\gcc\\x86_64-w64-mingw32\\13.1.0\\include\\c++\\x86_64-w64-mingw32","-isystem","D:\\QT\\Tools\\mingw1310_64\\lib\\gcc\\x86_64-w64-mingw32\\13.1.0\\include\\c++\\backward","-isystem","D:\\QT\\Tools\\QtCreator\\bin\\clang\\lib\\clang\\18\\include","-isystem","D:\\QT\\Tools\\mingw1310_64\\x86_64-w64-mingw32\\include","-fmessage-length=0","-fdiagnostics-show-note-include-stack","-fretain-comments-from-system-headers","-fmacro-backtrace-limit=0","-ferror-limit=1000","-x","c++-header","D:\\fly_manage_system_lxt\\mainwindow.h"],"directory":"D:/fly_manage_system_lxt/build/Desktop_Qt_6_8_0_MinGW_64_bit-Debug/.qtc_clangd","file":"D:/fly_manage_system_lxt/mainwindow.h"},{"arguments":["clang","-Wno-documentation-unknown-command","-Wno-unknown-warning-option","-Wno-unknown-pragmas","-nostdinc","-nostdinc++","-g","-std=gnu++1z","-Wall","-Wextra","-Wextra","-fexceptions","-mthreads","-fsyntax-only","-m64","--target=x86_64-w64-mingw32","-DUNICODE","-D_UNICODE","-DWIN32","-DMINGW_HAS_SECURE_API","-DQT_QML_DEBUG","-DQT_WIDGETS_LIB","-DQT_GUI_LIB","-DQT_CORE_LIB","-DQT_NEEDS_QMAIN","-DQ_CREATOR_RUN","-DQT_ANNOTATE_FUNCTION(x)=__attribute__((annotate(#x)))","-ID:\\QT\\Tools\\QtCreator\\share\\qtcreator\\cplusplus\\wrappedMingwHeaders","-ID:\\QT\\Tools\\QtCreator\\share\\qtcreator\\cplusplus\\wrappedQtHeaders","-ID:\\QT\\Tools\\QtCreator\\share\\qtcreator\\cplusplus\\wrappedQtHeaders\\QtCore","-ID:\\fly_manage_system_lxt","-ID:\\QT\\6.8.0\\mingw_64\\include","-ID:\\QT\\6.8.0\\mingw_64\\include\\QtWidgets","-ID:\\QT\\6.8.0\\mingw_64\\include\\QtGui","-ID:\\QT\\6.8.0\\mingw_64\\include\\QtCore","-ID:\\fly_manage_system_lxt\\build\\Desktop_Qt_6_8_0_MinGW_64_bit-Debug\\debug","-ID:\\fly_manage_system_lxt\\build\\Desktop_Qt_6_8_0_MinGW_64_bit-Debug","-ID:\\QT\\6.8.0\\mingw_64\\mkspecs\\win32-g++","-isystem","D:\\QT\\Tools\\mingw1310_64\\lib\\gcc\\x86_64-w64-mingw32\\13.1.0\\include\\c++","-isystem","D:\\QT\\Tools\\mingw1310_64\\lib\\gcc\\x86_64-w64-mingw32\\13.1.0\\include\\c++\\x86_64-w64-mingw32","-isystem","D:\\QT\\Tools\\mingw1310_64\\lib\\gcc\\x86_64-w64-mingw32\\13.1.0\\include\\c++\\backward","-isystem","D:\\QT\\Tools\\QtCreator\\bin\\clang\\lib\\clang\\18\\include","-isystem","D:\\QT\\Tools\\mingw1310_64\\x86_64-w64-mingw32\\include","-fmessage-length=0","-fdiagnostics-show-note-include-stack","-fretain-comments-from-system-headers","-fmacro-backtrace-limit=0","-ferror-limit=1000","-x","c++-header","D:\\fly_manage_system_lxt\\xitawindow.h"],"directory":"D:/fly_manage_system_lxt/build/Desktop_Qt_6_8_0_MinGW_64_bit-Debug/.qtc_clangd","file":"D:/fly_manage_system_lxt/xitawindow.h"},{"arguments":["clang","-Wno-documentation-unknown-command","-Wno-unknown-warning-option","-Wno-unknown-pragmas","-nostdinc","-nostdinc++","-g","-std=gnu++1z","-Wall","-Wextra","-Wextra","-fexceptions","-mthreads","-fsyntax-only","-m64","--target=x86_64-w64-mingw32","-DUNICODE","-D_UNICODE","-DWIN32","-DMINGW_HAS_SECURE_API","-DQT_QML_DEBUG","-DQT_WIDGETS_LIB","-DQT_GUI_LIB","-DQT_CORE_LIB","-DQT_NEEDS_QMAIN","-DQ_CREATOR_RUN","-DQT_ANNOTATE_FUNCTION(x)=__attribute__((annotate(#x)))","-ID:\\QT\\Tools\\QtCreator\\share\\qtcreator\\cplusplus\\wrappedMingwHeaders","-ID:\\QT\\Tools\\QtCreator\\share\\qtcreator\\cplusplus\\wrappedQtHeaders","-ID:\\QT\\Tools\\QtCreator\\share\\qtcreator\\cplusplus\\wrappedQtHeaders\\QtCore","-ID:\\fly_manage_system_lxt","-ID:\\QT\\6.8.0\\mingw_64\\include","-ID:\\QT\\6.8.0\\mingw_64\\include\\QtWidgets","-ID:\\QT\\6.8.0\\mingw_64\\include\\QtGui","-ID:\\QT\\6.8.0\\mingw_64\\include\\QtCore","-ID:\\fly_manage_system_lxt\\build\\Desktop_Qt_6_8_0_MinGW_64_bit-Debug\\debug","-ID:\\fly_manage_system_lxt\\build\\Desktop_Qt_6_8_0_MinGW_64_bit-Debug","-ID:\\QT\\6.8.0\\mingw_64\\mkspecs\\win32-g++","-isystem","D:\\QT\\Tools\\mingw1310_64\\lib\\gcc\\x86_64-w64-mingw32\\13.1.0\\include\\c++","-isystem","D:\\QT\\Tools\\mingw1310_64\\lib\\gcc\\x86_64-w64-mingw32\\13.1.0\\include\\c++\\x86_64-w64-mingw32","-isystem","D:\\QT\\Tools\\mingw1310_64\\lib\\gcc\\x86_64-w64-mingw32\\13.1.0\\include\\c++\\backward","-isystem","D:\\QT\\Tools\\QtCreator\\bin\\clang\\lib\\clang\\18\\include","-isystem","D:\\QT\\Tools\\mingw1310_64\\x86_64-w64-mingw32\\include","-fmessage-length=0","-fdiagnostics-show-note-include-stack","-fretain-comments-from-system-headers","-fmacro-backtrace-limit=0","-ferror-limit=1000","-x","c++-header","D:\\fly_manage_system_lxt\\yipuxilong.h"],"directory":"D:/fly_manage_system_lxt/build/Desktop_Qt_6_8_0_MinGW_64_bit-Debug/.qtc_clangd","file":"D:/fly_manage_system_lxt/yipuxilong.h"},{"arguments":["clang","-Wno-documentation-unknown-command","-Wno-unknown-warning-option","-Wno-unknown-pragmas","-nostdinc","-nostdinc++","-g","-std=gnu++1z","-Wall","-Wextra","-Wextra","-fexceptions","-mthreads","-fsyntax-only","-m64","--target=x86_64-w64-mingw32","-DUNICODE","-D_UNICODE","-DWIN32","-DMINGW_HAS_SECURE_API","-DQT_QML_DEBUG","-DQT_WIDGETS_LIB","-DQT_GUI_LIB","-DQT_CORE_LIB","-DQT_NEEDS_QMAIN","-DQ_CREATOR_RUN","-DQT_ANNOTATE_FUNCTION(x)=__attribute__((annotate(#x)))","-ID:\\QT\\Tools\\QtCreator\\share\\qtcreator\\cplusplus\\wrappedMingwHeaders","-ID:\\QT\\Tools\\QtCreator\\share\\qtcreator\\cplusplus\\wrappedQtHeaders","-ID:\\QT\\Tools\\QtCreator\\share\\qtcreator\\cplusplus\\wrappedQtHeaders\\QtCore","-ID:\\fly_manage_system_lxt","-ID:\\QT\\6.8.0\\mingw_64\\include","-ID:\\QT\\6.8.0\\mingw_64\\include\\QtWidgets","-ID:\\QT\\6.8.0\\mingw_64\\include\\QtGui","-ID:\\QT\\6.8.0\\mingw_64\\include\\QtCore","-ID:\\fly_manage_system_lxt\\build\\Desktop_Qt_6_8_0_MinGW_64_bit-Debug\\debug","-ID:\\fly_manage_system_lxt\\build\\Desktop_Qt_6_8_0_MinGW_64_bit-Debug","-ID:\\QT\\6.8.0\\mingw_64\\mkspecs\\win32-g++","-isystem","D:\\QT\\Tools\\mingw1310_64\\lib\\gcc\\x86_64-w64-mingw32\\13.1.0\\include\\c++","-isystem","D:\\QT\\Tools\\mingw1310_64\\lib\\gcc\\x86_64-w64-mingw32\\13.1.0\\include\\c++\\x86_64-w64-mingw32","-isystem","D:\\QT\\Tools\\mingw1310_64\\lib\\gcc\\x86_64-w64-mingw32\\13.1.0\\include\\c++\\backward","-isystem","D:\\QT\\Tools\\QtCreator\\bin\\clang\\lib\\clang\\18\\include","-isystem","D:\\QT\\Tools\\mingw1310_64\\x86_64-w64-mingw32\\include","-fmessage-length=0","-fdiagnostics-show-note-include-stack","-fretain-comments-from-system-headers","-fmacro-backtrace-limit=0","-ferror-limit=1000","-x","c++-header","D:\\fly_manage_system_lxt\\build\\Desktop_Qt_6_8_0_MinGW_64_bit-Debug\\ui_mainwindow.h"],"directory":"D:/fly_manage_system_lxt/build/Desktop_Qt_6_8_0_MinGW_64_bit-Debug/.qtc_clangd","file":"D:/fly_manage_system_lxt/build/Desktop_Qt_6_8_0_MinGW_64_bit-Debug/ui_mainwindow.h"},{"arguments":["clang","-Wno-documentation-unknown-command","-Wno-unknown-warning-option","-Wno-unknown-pragmas","-nostdinc","-nostdinc++","-g","-std=gnu++1z","-Wall","-Wextra","-Wextra","-fexceptions","-mthreads","-fsyntax-only","-m64","--target=x86_64-w64-mingw32","-DUNICODE","-D_UNICODE","-DWIN32","-DMINGW_HAS_SECURE_API","-DQT_QML_DEBUG","-DQT_WIDGETS_LIB","-DQT_GUI_LIB","-DQT_CORE_LIB","-DQT_NEEDS_QMAIN","-DQ_CREATOR_RUN","-DQT_ANNOTATE_FUNCTION(x)=__attribute__((annotate(#x)))","-ID:\\QT\\Tools\\QtCreator\\share\\qtcreator\\cplusplus\\wrappedMingwHeaders","-ID:\\QT\\Tools\\QtCreator\\share\\qtcreator\\cplusplus\\wrappedQtHeaders","-ID:\\QT\\Tools\\QtCreator\\share\\qtcreator\\cplusplus\\wrappedQtHeaders\\QtCore","-ID:\\fly_manage_system_lxt","-ID:\\QT\\6.8.0\\mingw_64\\include","-ID:\\QT\\6.8.0\\mingw_64\\include\\QtWidgets","-ID:\\QT\\6.8.0\\mingw_64\\include\\QtGui","-ID:\\QT\\6.8.0\\mingw_64\\include\\QtCore","-ID:\\fly_manage_system_lxt\\build\\Desktop_Qt_6_8_0_MinGW_64_bit-Debug\\debug","-ID:\\fly_manage_system_lxt\\build\\Desktop_Qt_6_8_0_MinGW_64_bit-Debug","-ID:\\QT\\6.8.0\\mingw_64\\mkspecs\\win32-g++","-isystem","D:\\QT\\Tools\\mingw1310_64\\lib\\gcc\\x86_64-w64-mingw32\\13.1.0\\include\\c++","-isystem","D:\\QT\\Tools\\mingw1310_64\\lib\\gcc\\x86_64-w64-mingw32\\13.1.0\\include\\c++\\x86_64-w64-mingw32","-isystem","D:\\QT\\Tools\\mingw1310_64\\lib\\gcc\\x86_64-w64-mingw32\\13.1.0\\include\\c++\\backward","-isystem","D:\\QT\\Tools\\QtCreator\\bin\\clang\\lib\\clang\\18\\include","-isystem","D:\\QT\\Tools\\mingw1310_64\\x86_64-w64-mingw32\\include","-fmessage-length=0","-fdiagnostics-show-note-include-stack","-fretain-comments-from-system-headers","-fmacro-backtrace-limit=0","-ferror-limit=1000","-x","c++-header","D:\\fly_manage_system_lxt\\build\\Desktop_Qt_6_8_0_MinGW_64_bit-Debug\\ui_xitawindow.h"],"directory":"D:/fly_manage_system_lxt/build/Desktop_Qt_6_8_0_MinGW_64_bit-Debug/.qtc_clangd","file":"D:/fly_manage_system_lxt/build/Desktop_Qt_6_8_0_MinGW_64_bit-Debug/ui_xitawindow.h"},{"arguments":["clang","-Wno-documentation-unknown-command","-Wno-unknown-warning-option","-Wno-unknown-pragmas","-nostdinc","-nostdinc++","-g","-std=gnu++1z","-Wall","-Wextra","-Wextra","-fexceptions","-mthreads","-fsyntax-only","-m64","--target=x86_64-w64-mingw32","-DUNICODE","-D_UNICODE","-DWIN32","-DMINGW_HAS_SECURE_API","-DQT_QML_DEBUG","-DQT_WIDGETS_LIB","-DQT_GUI_LIB","-DQT_CORE_LIB","-DQT_NEEDS_QMAIN","-DQ_CREATOR_RUN","-DQT_ANNOTATE_FUNCTION(x)=__attribute__((annotate(#x)))","-ID:\\QT\\Tools\\QtCreator\\share\\qtcreator\\cplusplus\\wrappedMingwHeaders","-ID:\\QT\\Tools\\QtCreator\\share\\qtcreator\\cplusplus\\wrappedQtHeaders","-ID:\\QT\\Tools\\QtCreator\\share\\qtcreator\\cplusplus\\wrappedQtHeaders\\QtCore","-ID:\\fly_manage_system_lxt","-ID:\\QT\\6.8.0\\mingw_64\\include","-ID:\\QT\\6.8.0\\mingw_64\\include\\QtWidgets","-ID:\\QT\\6.8.0\\mingw_64\\include\\QtGui","-ID:\\QT\\6.8.0\\mingw_64\\include\\QtCore","-ID:\\fly_manage_system_lxt\\build\\Desktop_Qt_6_8_0_MinGW_64_bit-Debug\\debug","-ID:\\fly_manage_system_lxt\\build\\Desktop_Qt_6_8_0_MinGW_64_bit-Debug","-ID:\\QT\\6.8.0\\mingw_64\\mkspecs\\win32-g++","-isystem","D:\\QT\\Tools\\mingw1310_64\\lib\\gcc\\x86_64-w64-mingw32\\13.1.0\\include\\c++","-isystem","D:\\QT\\Tools\\mingw1310_64\\lib\\gcc\\x86_64-w64-mingw32\\13.1.0\\include\\c++\\x86_64-w64-mingw32","-isystem","D:\\QT\\Tools\\mingw1310_64\\lib\\gcc\\x86_64-w64-mingw32\\13.1.0\\include\\c++\\backward","-isystem","D:\\QT\\Tools\\QtCreator\\bin\\clang\\lib\\clang\\18\\include","-isystem","D:\\QT\\Tools\\mingw1310_64\\x86_64-w64-mingw32\\include","-fmessage-length=0","-fdiagnostics-show-note-include-stack","-fretain-comments-from-system-headers","-fmacro-backtrace-limit=0","-ferror-limit=1000","-x","c++-header","D:\\fly_manage_system_lxt\\build\\Desktop_Qt_6_8_0_MinGW_64_bit-Debug\\ui_betawindow.h"],"directory":"D:/fly_manage_system_lxt/build/Desktop_Qt_6_8_0_MinGW_64_bit-Debug/.qtc_clangd","file":"D:/fly_manage_system_lxt/build/Desktop_Qt_6_8_0_MinGW_64_bit-Debug/ui_betawindow.h"},{"arguments":["clang","-Wno-documentation-unknown-command","-Wno-unknown-warning-option","-Wno-unknown-pragmas","-nostdinc","-nostdinc++","-g","-std=gnu++1z","-Wall","-Wextra","-Wextra","-fexceptions","-mthreads","-fsyntax-only","-m64","--target=x86_64-w64-mingw32","-DUNICODE","-D_UNICODE","-DWIN32","-DMINGW_HAS_SECURE_API","-DQT_QML_DEBUG","-DQT_WIDGETS_LIB","-DQT_GUI_LIB","-DQT_CORE_LIB","-DQT_NEEDS_QMAIN","-DQ_CREATOR_RUN","-DQT_ANNOTATE_FUNCTION(x)=__attribute__((annotate(#x)))","-ID:\\QT\\Tools\\QtCreator\\share\\qtcreator\\cplusplus\\wrappedMingwHeaders","-ID:\\QT\\Tools\\QtCreator\\share\\qtcreator\\cplusplus\\wrappedQtHeaders","-ID:\\QT\\Tools\\QtCreator\\share\\qtcreator\\cplusplus\\wrappedQtHeaders\\QtCore","-ID:\\fly_manage_system_lxt","-ID:\\QT\\6.8.0\\mingw_64\\include","-ID:\\QT\\6.8.0\\mingw_64\\include\\QtWidgets","-ID:\\QT\\6.8.0\\mingw_64\\include\\QtGui","-ID:\\QT\\6.8.0\\mingw_64\\include\\QtCore","-ID:\\fly_manage_system_lxt\\build\\Desktop_Qt_6_8_0_MinGW_64_bit-Debug\\debug","-ID:\\fly_manage_system_lxt\\build\\Desktop_Qt_6_8_0_MinGW_64_bit-Debug","-ID:\\QT\\6.8.0\\mingw_64\\mkspecs\\win32-g++","-isystem","D:\\QT\\Tools\\mingw1310_64\\lib\\gcc\\x86_64-w64-mingw32\\13.1.0\\include\\c++","-isystem","D:\\QT\\Tools\\mingw1310_64\\lib\\gcc\\x86_64-w64-mingw32\\13.1.0\\include\\c++\\x86_64-w64-mingw32","-isystem","D:\\QT\\Tools\\mingw1310_64\\lib\\gcc\\x86_64-w64-mingw32\\13.1.0\\include\\c++\\backward","-isystem","D:\\QT\\Tools\\QtCreator\\bin\\clang\\lib\\clang\\18\\include","-isystem","D:\\QT\\Tools\\mingw1310_64\\x86_64-w64-mingw32\\include","-fmessage-length=0","-fdiagnostics-show-note-include-stack","-fretain-comments-from-system-headers","-fmacro-backtrace-limit=0","-ferror-limit=1000","-x","c++-header","D:\\fly_manage_system_lxt\\build\\Desktop_Qt_6_8_0_MinGW_64_bit-Debug\\ui_yipuxilong.h"],"directory":"D:/fly_manage_system_lxt/build/Desktop_Qt_6_8_0_MinGW_64_bit-Debug/.qtc_clangd","file":"D:/fly_manage_system_lxt/build/Desktop_Qt_6_8_0_MinGW_64_bit-Debug/ui_yipuxilong.h"},{"arguments":["clang","-Wno-documentation-unknown-command","-Wno-unknown-warning-option","-Wno-unknown-pragmas","-nostdinc","-nostdinc++","-g","-std=gnu++1z","-Wall","-Wextra","-Wextra","-fexceptions","-mthreads","-fsyntax-only","-m64","--target=x86_64-w64-mingw32","-DUNICODE","-D_UNICODE","-DWIN32","-DMINGW_HAS_SECURE_API","-DQT_QML_DEBUG","-DQT_WIDGETS_LIB","-DQT_GUI_LIB","-DQT_CORE_LIB","-DQT_NEEDS_QMAIN","-DQ_CREATOR_RUN","-DQT_ANNOTATE_FUNCTION(x)=__attribute__((annotate(#x)))","-ID:\\QT\\Tools\\QtCreator\\share\\qtcreator\\cplusplus\\wrappedMingwHeaders","-ID:\\QT\\Tools\\QtCreator\\share\\qtcreator\\cplusplus\\wrappedQtHeaders","-ID:\\QT\\Tools\\QtCreator\\share\\qtcreator\\cplusplus\\wrappedQtHeaders\\QtCore","-ID:\\fly_manage_system_lxt","-ID:\\QT\\6.8.0\\mingw_64\\include","-ID:\\QT\\6.8.0\\mingw_64\\include\\QtWidgets","-ID:\\QT\\6.8.0\\mingw_64\\include\\QtGui","-ID:\\QT\\6.8.0\\mingw_64\\include\\QtCore","-ID:\\fly_manage_system_lxt\\build\\Desktop_Qt_6_8_0_MinGW_64_bit-Debug\\debug","-ID:\\fly_manage_system_lxt\\build\\Desktop_Qt_6_8_0_MinGW_64_bit-Debug","-ID:\\QT\\6.8.0\\mingw_64\\mkspecs\\win32-g++","-isystem","D:\\QT\\Tools\\mingw1310_64\\lib\\gcc\\x86_64-w64-mingw32\\13.1.0\\include\\c++","-isystem","D:\\QT\\Tools\\mingw1310_64\\lib\\gcc\\x86_64-w64-mingw32\\13.1.0\\include\\c++\\x86_64-w64-mingw32","-isystem","D:\\QT\\Tools\\mingw1310_64\\lib\\gcc\\x86_64-w64-mingw32\\13.1.0\\include\\c++\\backward","-isystem","D:\\QT\\Tools\\QtCreator\\bin\\clang\\lib\\clang\\18\\include","-isystem","D:\\QT\\Tools\\mingw1310_64\\x86_64-w64-mingw32\\include","-fmessage-length=0","-fdiagnostics-show-note-include-stack","-fretain-comments-from-system-headers","-fmacro-backtrace-limit=0","-ferror-limit=1000","-x","c++-header","D:\\fly_manage_system_lxt\\build\\Desktop_Qt_6_8_0_MinGW_64_bit-Debug\\ui_gamawindow.h"],"directory":"D:/fly_manage_system_lxt/build/Desktop_Qt_6_8_0_MinGW_64_bit-Debug/.qtc_clangd","file":"D:/fly_manage_system_lxt/build/Desktop_Qt_6_8_0_MinGW_64_bit-Debug/ui_gamawindow.h"}]